khmerdocparser/__init__.py
khmerdocparser/main.py
khmerdocparser-0.3.0.dist-info/licenses/LICENSE
khmerdocparser-0.3.0.dist-info/METADATA
khmerdocparser-0.3.0.dist-info/WHEEL
khmerdocparser-0.3.0.dist-info/entry_points.txt
khmerdocparser-0.3.0.dist-info/top_level.txt
khmerdocparser-0.3.0.dist-info/RECORD
