Metadata-Version: 2.4
Name: khmerdocparser
Version: 0.3.0
Summary: A smart Python tool to extract Khmer text from PDF and image files, using OCR for scanned documents and direct extraction for native PDFs.
Author-email: Nimol Thuon <nimol.thuon@gmail.com>
Project-URL: Homepage, https://github.com/your_username/khmerdocparser
Project-URL: Bug Tracker, https://github.com/your_username/khmerdocparser/issues
Classifier: Programming Language :: Python :: 3
Classifier: License :: OSI Approved :: MIT License
Classifier: Operating System :: OS Independent
Classifier: Topic :: Text Processing
Classifier: Topic :: Utilities
Requires-Python: >=3.8
License-File: LICENSE
Requires-Dist: pdf2image
Requires-Dist: pytesseract
Requires-Dist: Pillow
Requires-Dist: opencv-python-headless
Requires-Dist: pdfplumber
Requires-Dist: tqdm
Dynamic: license-file
